aio_appstoreserverlibrary-0.1.0.dist-info/METADATA
aio_appstoreserverlibrary-0.1.0.dist-info/WHEEL
aio_appstoreserverlibrary-0.1.0.dist-info/licenses/LICENSE
aio_appstoreserverlibrary/__init__.py
aio_appstoreserverlibrary/api_client.py
aio_appstoreserverlibrary/const.py
aio_appstoreserverlibrary-0.1.0.dist-info/RECORD
