Metadata-Version: 2.1
Name: aio-appstoreserverlibrary
Version: 0.1.0
Summary: app-store-server-library-python asyncio API client, based on official version.
Author-Email: Kevin Lee <363344+ipfans@users.noreply.github.com>
License: MIT
Requires-Python: <4,>=3.8
Requires-Dist: app-store-server-library>=1.0.0
Requires-Dist: httpx>=0.26.0
